Metadata-Version: 2.1
Name: discli
Version: 1.1.2
Summary: 🎲 Discord Bot CLI for creating / deploying your discord bots!
Home-page: https://github.com/zenqii/discli
Author: Zenqi
License: MIT
Download-URL: https://github.com/zenqii/discli/tarball/main
Keywords: command line,discord.py,cli
Platform: Windows
Classifier: Development Status :: 4 - Beta
Classifier: Intended Audience :: Developers
Classifier: Intended Audience :: Education
Classifier: License :: OSI Approved :: MIT License
Classifier: Natural Language :: English
Classifier: Operating System :: Microsoft :: Windows
Classifier: Programming Language :: Python :: 3.5
Classifier: Programming Language :: Python :: 3.6
Classifier: Programming Language :: Python :: 3.7
Classifier: Programming Language :: Python :: 3.8
Classifier: Topic :: Software Development
Classifier: Topic :: Software Development :: Libraries :: Python Modules
Requires-Python: >=3.5
